LICENSE
MANIFEST.in
README.rst
setup.py
Flask_Views.egg-info/PKG-INFO
Flask_Views.egg-info/SOURCES.txt
Flask_Views.egg-info/dependency_links.txt
Flask_Views.egg-info/not-zip-safe
Flask_Views.egg-info/requires.txt
Flask_Views.egg-info/top_level.txt
flask_views/__init__.py
flask_views/base.py
flask_views/edit.py
flask_views/json.py
flask_views/db/__init__.py
flask_views/db/mongoengine/__init__.py
flask_views/db/mongoengine/detail.py
flask_views/db/mongoengine/edit.py
flask_views/db/mongoengine/json.py
flask_views/tests/__init__.py
flask_views/tests/__init__.pyc
flask_views/tests/functional/__init__.py
flask_views/tests/functional/__init__.pyc
flask_views/tests/functional/base.py
flask_views/tests/functional/base.pyc
flask_views/tests/functional/test_base.py
flask_views/tests/functional/test_base.pyc
flask_views/tests/functional/test_edit.py
flask_views/tests/functional/test_edit.pyc
flask_views/tests/functional/test_json.py
flask_views/tests/functional/test_json.pyc
flask_views/tests/functional/db/__init__.py
flask_views/tests/functional/db/__init__.pyc
flask_views/tests/functional/db/mongoengine/__init__.py
flask_views/tests/functional/db/mongoengine/__init__.pyc
flask_views/tests/functional/db/mongoengine/base.py
flask_views/tests/functional/db/mongoengine/base.pyc
flask_views/tests/functional/db/mongoengine/test_detail.py
flask_views/tests/functional/db/mongoengine/test_detail.pyc
flask_views/tests/functional/db/mongoengine/test_edit.py
flask_views/tests/functional/db/mongoengine/test_edit.pyc
flask_views/tests/functional/db/mongoengine/test_json.py
flask_views/tests/functional/db/mongoengine/test_json.pyc
flask_views/tests/functional/templates/detail_template.html
flask_views/tests/functional/templates/form_view.html
flask_views/tests/functional/templates/model_form_view.html
flask_views/tests/functional/templates/template_view.html
flask_views/tests/unit/__init__.py
flask_views/tests/unit/__init__.pyc
flask_views/tests/unit/test_base.py
flask_views/tests/unit/test_base.pyc
flask_views/tests/unit/test_edit.py
flask_views/tests/unit/test_edit.pyc
flask_views/tests/unit/test_json.py
flask_views/tests/unit/test_json.pyc
flask_views/tests/unit/db/__init__.py
